{
	"info": {
		"_postman_id": "5e9a3a97-fb9b-4e8b-b98b-6426da8d56c5",
		"name": "HabitanteViviendaTest.postman_collection",
		"schema": "https://schema.getpostman.com/json/collection/v2.1.0/collection.json",
		"_exporter_id": "32909011"
	},
	"item": [
		{
			"name": "Crear un habitante",
			"event": [
				{
					"listen": "test",
					"script": {
						"exec": [
							"var data = pm.response.json()\r",
							"pm.globals.set(\"habitante_id_1\", data.id);\r",
							"\r",
							"pm.test(\"Status code is 201\", function(){\r",
							"    pm.response.to.have.status(201)\r",
							"});\r",
							""
						],
						"type": "text/javascript",
						"packages": {}
					}
				}
			],
			"request": {
				"method": "POST",
				"header": [],
				"body": {
					"mode": "raw",
					"raw": "{   \r\n    \"nombre\" : \"Carlos Sanchez\",\r\n    \"cedula\" : 1234567891\r\n}",
					"options": {
						"raw": {
							"language": "json"
						}
					}
				},
				"url": {
					"raw": "{{baseUrl}}/habitantes",
					"host": [
						"{{baseUrl}}"
					],
					"path": [
						"habitantes"
					]
				},
				"description": "\"Si se devuelve 202 el request fue perfecto\""
			},
			"response": [
				{
					"name": "Crear un habitante",
					"originalRequest": {
						"method": "POST",
						"header": [],
						"body": {
							"mode": "raw",
							"raw": "{   \r\n    \"nombre\" : \"Carlos Sanchez\",\r\n    \"cedula\" : 1234567891\r\n}",
							"options": {
								"raw": {
									"language": "json"
								}
							}
						},
						"url": {
							"raw": "{{baseUrl}}/habitantes",
							"host": [
								"{{baseUrl}}"
							],
							"path": [
								"habitantes"
							]
						}
					},
					"_postman_previewlanguage": null,
					"header": null,
					"cookie": [],
					"body": null
				}
			]
		},
		{
			"name": "Crear una vivienda",
			"event": [
				{
					"listen": "test",
					"script": {
						"exec": [
							"var data = pm.response.json()\r",
							"pm.globals.set(\"vivienda_id_2\", data.id);\r",
							"\r",
							"pm.test(\"Status code is 201\", function(){\r",
							"    pm.response.to.have.status(201)\r",
							"});\r",
							""
						],
						"type": "text/javascript",
						"packages": {}
					}
				}
			],
			"request": {
				"method": "POST",
				"header": [],
				"body": {
					"mode": "raw",
					"raw": "{\r\n    \"nombre\":\"Habitacion unica\",\r\n    \"precio\": 1000000.00,\r\n    \"descripcion\": \"Perfecto para un estudiante joven\",\r\n    \"tamano\":80,\r\n    \"estrato\": 3,\r\n    \"fotos\":\"https://images.app.goo.gl/nP9QfwVN2GF4vNXF6\",\r\n    \"restricciones\":\"No se aceptan mascotas\",\r\n    \"tipo\":1,\r\n    \"contacto\":\"www.cityU.com\",\r\n    \"direccion\":\"cra 1a #19-23\",\r\n    \"ocupada\":false,\r\n    \"coordX\":10000.00,\r\n    \"coordY\":10000.00,\r\n    \"propietario\":{\"id\":{{propietario_id_3}}}\r\n\r\n}",
					"options": {
						"raw": {
							"language": "json"
						}
					}
				},
				"url": {
					"raw": "{{baseUrl}}/viviendas/{{vivienda_id_2}}/habitantes/{{habitante_id_1}}",
					"host": [
						"{{baseUrl}}"
					],
					"path": [
						"viviendas",
						"{{vivienda_id_2}}",
						"habitantes",
						"{{habitante_id_1}}"
					]
				}
			},
			"response": [
				{
					"name": "Crear una vivienda",
					"originalRequest": {
						"method": "POST",
						"header": [],
						"body": {
							"mode": "raw",
							"raw": "{\r\n    \"nombre\":\"Habitacion unica\",\r\n    \"precio\": 1000000.00,\r\n    \"descripcion\": \"Perfecto para un estudiante joven\",\r\n    \"tamano\":80,\r\n    \"estrato\": 3,\r\n    \"fotos\":\"https://images.app.goo.gl/nP9QfwVN2GF4vNXF6\",\r\n    \"restricciones\":\"No se aceptan mascotas\",\r\n    \"tipo\":1,\r\n    \"contacto\":\"www.cityU.com\",\r\n    \"direccion\":\"cra 1a #19-23\",\r\n    \"ocupada\":false,\r\n    \"coordX\":10000.00,\r\n    \"coordY\":10000.00,\r\n    \"propietario\":{\"id\":{{propietario_id_3}}}\r\n\r\n}",
							"options": {
								"raw": {
									"language": "json"
								}
							}
						},
						"url": {
							"raw": "{{baseUrl}}/viviendas",
							"host": [
								"{{baseUrl}}"
							],
							"path": [
								"viviendas"
							]
						}
					},
					"_postman_previewlanguage": null,
					"header": null,
					"cookie": [],
					"body": null
				}
			]
		},
		{
			"name": "Agregar vivienda a un habitante",
			"event": [
				{
					"listen": "test",
					"script": {
						"exec": [
							"pm.test(\"Status code is 200\", function () {\r",
							"   pm.response.to.have.status(200);\r",
							"});"
						],
						"type": "text/javascript",
						"packages": {}
					}
				}
			],
			"request": {
				"method": "POST",
				"header": [],
				"url": {
					"raw": "{{baseUrl}}/habitantes/{{habitante_id}}/vivienda/{{vivienda_id_1}}",
					"host": [
						"{{baseUrl}}"
					],
					"path": [
						"habitantes",
						"{{habitante_id}}",
						"vivienda",
						"{{vivienda_id_1}}"
					]
				}
			},
			"response": []
		},
		{
			"name": "Obtener vivienda de un habitante",
			"event": [
				{
					"listen": "test",
					"script": {
						"exec": [
							"pm.test(\"Status code is 200\", function () {\r",
							"   pm.response.to.have.status(200);\r",
							"});"
						],
						"type": "text/javascript",
						"packages": {}
					}
				}
			],
			"request": {
				"method": "GET",
				"header": [],
				"url": {
					"raw": "{{baseUrl}}/habitantes/{{habitante_id}}/viviendas/{{vivienda_id_1}}.",
					"host": [
						"{{baseUrl}}"
					],
					"path": [
						"habitantes",
						"{{habitante_id}}",
						"viviendas",
						"{{vivienda_id_1}}."
					]
				}
			},
			"response": []
		},
		{
			"name": "Obtener una vivienda no asociada a un habitante",
			"event": [
				{
					"listen": "test",
					"script": {
						"exec": [
							"pm.test(\"Status code is 412\", function () {\r",
							"   pm.response.to.have.status(412);\r",
							"});\r",
							"\r",
							"pm.test(\"Get expected error message\", function () {\r",
							"   var data = pm.response.json();\r",
							"   pm.expect(data.apierror.message).to.eql(\"La vivienda no esta asociada al habitante\");\r",
							"});"
						],
						"type": "text/javascript",
						"packages": {}
					}
				}
			],
			"request": {
				"method": "GET",
				"header": [],
				"url": {
					"raw": "{{baseUrl}}/habitantes/{{habitante_id}}/viviendas/{{vivienda_id_2}}\n\n",
					"host": [
						"{{baseUrl}}"
					],
					"path": [
						"habitantes",
						"{{habitante_id}}",
						"viviendas",
						"{{vivienda_id_2}}\n\n"
					]
				}
			},
			"response": []
		},
		{
			"name": "Obtener una vivienda que no existe de un habitante",
			"event": [
				{
					"listen": "test",
					"script": {
						"exec": [
							"pm.test(\"Status code is 404\", function () {\r",
							"   pm.response.to.have.status(404);\r",
							"});\r",
							"\r",
							"pm.test(\"Get expected error message\", function () {\r",
							"   var data = pm.response.json();\r",
							"   pm.expect(data.apierror.message).to.eql(\"El habitante con el id no fue encontrado\");\r",
							"});"
						],
						"type": "text/javascript",
						"packages": {}
					}
				}
			],
			"request": {
				"method": "GET",
				"header": [],
				"url": {
					"raw": "{{baseUrl}}/habitantes/{{habitantes_id}}/vivienda/0\n\n",
					"host": [
						"{{baseUrl}}"
					],
					"path": [
						"habitantes",
						"{{habitantes_id}}",
						"vivienda",
						"0\n\n"
					]
				}
			},
			"response": []
		},
		{
			"name": "Asociar vivienda a un habitante",
			"event": [
				{
					"listen": "test",
					"script": {
						"exec": [
							"pm.test(\"Status code is 200\", function () {\r",
							"   pm.response.to.have.status(200);\r",
							"});"
						],
						"type": "text/javascript",
						"packages": {}
					}
				}
			],
			"request": {
				"method": "PUT",
				"header": [],
				"body": {
					"mode": "raw",
					"raw": "[\r\n    {\r\n        \"id\": {{vivienda_id}}\r\n    },\r\n    {\r\n\r\n        \"id\": {{vivienda_id_2}}\r\n    }\r\n]",
					"options": {
						"raw": {
							"language": "json"
						}
					}
				},
				"url": {
					"raw": "{{baseUrl}}/habitante/{{habitante_id}}/vivienda",
					"host": [
						"{{baseUrl}}"
					],
					"path": [
						"habitante",
						"{{habitante_id}}",
						"vivienda"
					]
				}
			},
			"response": []
		},
		{
			"name": "Borrar vivienda a un habitante",
			"event": [
				{
					"listen": "test",
					"script": {
						"exec": [
							"pm.test(\"Status code is 204\", function () {\r",
							"   pm.response.to.have.status(204);\r",
							"});"
						],
						"type": "text/javascript",
						"packages": {}
					}
				}
			],
			"request": {
				"method": "DELETE",
				"header": [],
				"url": {
					"raw": "{{baseUrl}}/habitantes/{{habitante_id}}/viviendas{{vivienda_id_2}}\n\n",
					"host": [
						"{{baseUrl}}"
					],
					"path": [
						"habitantes",
						"{{habitante_id}}",
						"viviendas{{vivienda_id_2}}\n\n"
					]
				}
			},
			"response": []
		},
		{
			"name": "Borrar una vivienda",
			"event": [
				{
					"listen": "test",
					"script": {
						"exec": [
							"pm.test(\"Status code is 204\", function () {\r",
							"   pm.response.to.have.status(204);\r",
							"});"
						],
						"type": "text/javascript",
						"packages": {}
					}
				}
			],
			"request": {
				"method": "DELETE",
				"header": [],
				"url": {
					"raw": "{{baseUrl}}/viviendas/{{viviendas_id_1}}",
					"host": [
						"{{baseUrl}}"
					],
					"path": [
						"viviendas",
						"{{viviendas_id_1}}"
					]
				}
			},
			"response": []
		},
		{
			"name": "Borrar un habitante",
			"event": [
				{
					"listen": "test",
					"script": {
						"exec": [
							"pm.test(\"Status code is 204\", function () {\r",
							"   pm.response.to.have.status(204);\r",
							"});"
						],
						"type": "text/javascript",
						"packages": {}
					}
				}
			],
			"request": {
				"method": "DELETE",
				"header": [],
				"url": {
					"raw": "{{baseUrl}}/habitantes/{{habitante_id_1}}",
					"host": [
						"{{baseUrl}}"
					],
					"path": [
						"habitantes",
						"{{habitante_id_1}}"
					]
				}
			},
			"response": []
		}
	]
}