{
	"info": {
		"_postman_id": "6e09bbbc-99ba-4c0c-97e4-53786f685c19",
		"name": "ServicioViviendaTest",
		"schema": "https://schema.getpostman.com/json/collection/v2.1.0/collection.json",
		"_exporter_id": "32527961"
	},
	"item": [
		{
			"name": "Crear Propietario",
			"event": [
				{
					"listen": "test",
					"script": {
						"exec": [
							"var data = pm.response.json()",
							"pm.globals.set(\"propietario_id_1\",data.id);",
							"",
							"pm.test(\"Status code is 201\", function() {",
							"    pm.response.to.have.status(201);",
							"})"
						],
						"type": "text/javascript",
						"packages": {}
					}
				}
			],
			"request": {
				"method": "POST",
				"header": [],
				"body": {
					"mode": "raw",
					"raw": "{\n    \"foto\": \"https://en.wikipedia.org/wiki/Sam_Altman#/media/File:Sam_Altman_CropEdit_James_Tamim.jpg\",\n    \"nombre\": \"Sam Altman\", \n    \"celular\": 987654,\n    \"correo\": \"SamyAltman@gmail.com\"\n}",
					"options": {
						"raw": {
							"language": "json"
						}
					}
				},
				"url": {
					"raw": "{{baseUrl}}/propietarios",
					"host": [
						"{{baseUrl}}"
					],
					"path": [
						"propietarios"
					]
				}
			},
			"response": []
		},
		{
			"name": "Crear Vivienda",
			"event": [
				{
					"listen": "test",
					"script": {
						"exec": [
							"var data = pm.response.json()",
							"pm.globals.set(\"servicio_id_1\",data.id);",
							"",
							"pm.test(\"Status code is 201\", function() {",
							"    pm.response.to.have.status(201);",
							"})"
						],
						"type": "text/javascript",
						"packages": {}
					}
				}
			],
			"request": {
				"method": "POST",
				"header": [],
				"body": {
					"mode": "raw",
					"raw": "{\n    \"nombre\":\"Habitacion unica\",\n    \"precio\": 2000000.00,\n    \"descripcion\": \"Habitación  en apartamnetop compartido\",\n    \"tamano\":45,\n    \"estrato\": 5,\n    \"fotos\":\"https://www.reddit.com/r/DesignMyRoom/comments/sggy1y/got_my_new_hostel_room_lets_just_say_the_past/\",\n    \"restricciones\":\"No se puede fumar en el apartamneto\",\n    \"tipo\":1,\n    \"contacto\":\"www.cityO.com\",\n    \"direccion\":\"cra 5a #12-53\",\n    \"ocupada\":false,\n    \"coordX\":100.0,\n    \"coordY\":1000.0,\n    \"propietario\":{\"id\":{{propietario_id_1}}}\n\n}",
					"options": {
						"raw": {
							"language": "json"
						}
					}
				},
				"url": {
					"raw": "{{baseUrl}}/viviendas",
					"host": [
						"{{baseUrl}}"
					],
					"path": [
						"viviendas"
					]
				}
			},
			"response": []
		},
		{
			"name": "Crear Vivienda Copy",
			"event": [
				{
					"listen": "test",
					"script": {
						"exec": [
							"var data = pm.response.json()",
							"pm.globals.set(\"servicio_id_1\",data.id);",
							"",
							"pm.test(\"Status code is 201\", function() {",
							"    pm.response.to.have.status(201);",
							"})"
						],
						"type": "text/javascript",
						"packages": {}
					}
				}
			],
			"request": {
				"method": "POST",
				"header": [],
				"body": {
					"mode": "raw",
					"raw": "{\n    \"nombre\":\"Habitacion unica\",\n    \"precio\": 2000000.00,\n    \"descripcion\": \"Habitación  en apartamnetop compartido\",\n    \"tamano\":45,\n    \"estrato\": 5,\n    \"fotos\":\"https://www.reddit.com/r/DesignMyRoom/comments/sggy1y/got_my_new_hostel_room_lets_just_say_the_past/\",\n    \"restricciones\":\"No se puede fumar en el apartamneto\",\n    \"tipo\":1,\n    \"contacto\":\"www.cityO.com\",\n    \"direccion\":\"cra 5a #12-53\",\n    \"ocupada\":false,\n    \"coordX\":100.0,\n    \"coordY\":1000.0,\n    \"propietario\":{\"id\":{{propietario_id_1}}}\n\n}",
					"options": {
						"raw": {
							"language": "json"
						}
					}
				},
				"url": {
					"raw": "{{baseUrl}}/viviendas",
					"host": [
						"{{baseUrl}}"
					],
					"path": [
						"viviendas"
					]
				}
			},
			"response": []
		},
		{
			"name": "Crear Servicio",
			"event": [
				{
					"listen": "test",
					"script": {
						"exec": [
							"var data = pm.response.json()",
							"pm.globals.set(\"servicio_id_1\",data.id);",
							"",
							"pm.test(\"Status code is 201\", function() {",
							"    pm.response.to.have.status(201);",
							"})"
						],
						"type": "text/javascript",
						"packages": {}
					}
				}
			],
			"request": {
				"method": "POST",
				"header": [],
				"body": {
					"mode": "raw",
					"raw": "{\n    \"nombre\": \"Hornitos\",\n    \"costoAdicional\":0,\n    \"tipo\":4\n}",
					"options": {
						"raw": {
							"language": "json"
						}
					}
				},
				"url": {
					"raw": "{{baseUrl}}/servicios",
					"host": [
						"{{baseUrl}}"
					],
					"path": [
						"servicios"
					]
				}
			},
			"response": []
		},
		{
			"name": "Agregar vivienda a servicio",
			"event": [
				{
					"listen": "test",
					"script": {
						"exec": [
							"pm.test(\"Status code is 200\", function () {",
							"   pm.response.to.have.status(200);",
							"});"
						],
						"type": "text/javascript",
						"packages": {}
					}
				}
			],
			"request": {
				"method": "POST",
				"header": [],
				"url": {
					"raw": "{{baseUrl}}/servicios/{{servicio_id_1}}/viviendas/{{vivienda_id_1}}",
					"host": [
						"{{baseUrl}}"
					],
					"path": [
						"servicios",
						"{{servicio_id_1}}",
						"viviendas",
						"{{vivienda_id_1}}"
					]
				}
			},
			"response": []
		},
		{
			"name": "Agregar vivienda ID inexistente servicio",
			"event": [
				{
					"listen": "test",
					"script": {
						"exec": [
							"pm.test(\"Status code is 404\", function () {",
							"   pm.response.to.have.status(404);",
							"});",
							"",
							"pm.test(\"Get expected error message\", function () {",
							"   var data = pm.response.json();",
							"   pm.expect(data.apierror.message).to.eql(\"La vivienda esta vacia.\");",
							"});"
						],
						"type": "text/javascript",
						"packages": {}
					}
				}
			],
			"request": {
				"method": "POST",
				"header": [],
				"url": {
					"raw": "{{baseUrl}}/servicios/{{servicio_id_1}}/viviendas/0",
					"host": [
						"{{baseUrl}}"
					],
					"path": [
						"servicios",
						"{{servicio_id_1}}",
						"viviendas",
						"0"
					]
				}
			},
			"response": []
		},
		{
			"name": "Obtener vivienda servicio con id",
			"event": [
				{
					"listen": "test",
					"script": {
						"exec": [
							"pm.test(\"Status code is 200\", function () {",
							"   pm.response.to.have.status(200);",
							"});",
							""
						],
						"type": "text/javascript",
						"packages": {}
					}
				}
			],
			"request": {
				"method": "GET",
				"header": [],
				"url": {
					"raw": "{{baseUrl}}/servicios/{{servicio_id_1}}/viviendas/{{vivienda_id_1}}",
					"host": [
						"{{baseUrl}}"
					],
					"path": [
						"servicios",
						"{{servicio_id_1}}",
						"viviendas",
						"{{vivienda_id_1}}"
					]
				}
			},
			"response": []
		},
		{
			"name": "Obtener vivienda sin id",
			"event": [
				{
					"listen": "test",
					"script": {
						"exec": [
							"pm.test(\"Status code is 404\", function () {",
							"   pm.response.to.have.status(404);",
							"});",
							"",
							"pm.test(\"Get expected error message\", function () {",
							"   var data = pm.response.json();",
							"   pm.expect(data.apierror.message).to.eql(\"La vivienda esta vacia.\");",
							"});"
						],
						"type": "text/javascript",
						"packages": {}
					}
				}
			],
			"request": {
				"method": "GET",
				"header": [],
				"url": {
					"raw": "{{baseUrl}}/servicios/{{servicio_id_1}}/viviendas/0",
					"host": [
						"{{baseUrl}}"
					],
					"path": [
						"servicios",
						"{{servicio_id_1}}",
						"viviendas",
						"0"
					]
				}
			},
			"response": []
		},
		{
			"name": "Obtener vivienda no asociada al servicio",
			"event": [
				{
					"listen": "test",
					"script": {
						"exec": [
							"pm.test(\"Status code is 404\", function () {",
							"   pm.response.to.have.status(404);",
							"});",
							"",
							"pm.test(\"Get expected error message\", function () {",
							"   var data = pm.response.json();",
							"   pm.expect(data.apierror.message).to.eql(\"La vivienda esta vacia.\");",
							"});",
							""
						],
						"type": "text/javascript",
						"packages": {}
					}
				}
			],
			"request": {
				"method": "GET",
				"header": [],
				"url": {
					"raw": "{{baseUrl}}/servicios/{{servicio_id_1}}/viviendas/{{vivienda_id_2}}",
					"host": [
						"{{baseUrl}}"
					],
					"path": [
						"servicios",
						"{{servicio_id_1}}",
						"viviendas",
						"{{vivienda_id_2}}"
					]
				}
			},
			"response": []
		},
		{
			"name": "Obtener Todas las viviendas servicio",
			"event": [
				{
					"listen": "test",
					"script": {
						"exec": [
							"pm.test('Number of viviendas > ' + 0, function () {",
							"   var data = pm.response.json()",
							"   pm.expect(data.length).to.greaterThan(0)",
							"});",
							"",
							"pm.test(\"Status code is 200\", function () {",
							"   pm.response.to.have.status(200);",
							"});"
						],
						"type": "text/javascript",
						"packages": {}
					}
				}
			],
			"request": {
				"method": "GET",
				"header": [],
				"url": {
					"raw": "{{baseUrl}}/servicios/{{servicio_id_1}}/viviendas",
					"host": [
						"{{baseUrl}}"
					],
					"path": [
						"servicios",
						"{{servicio_id_1}}",
						"viviendas"
					]
				}
			},
			"response": []
		},
		{
			"name": "Borra una vivienda de un servicio",
			"event": [
				{
					"listen": "test",
					"script": {
						"exec": [
							"pm.test(\"Status code is 204\", function () {",
							"   pm.response.to.have.status(204);",
							"});"
						],
						"type": "text/javascript",
						"packages": {}
					}
				}
			],
			"request": {
				"method": "DELETE",
				"header": [],
				"url": {
					"raw": "{{baseUrl}}/servicios/{{servicio_id_1}}/viviendas/{{vivienda_id_1}}",
					"host": [
						"{{baseUrl}}"
					],
					"path": [
						"servicios",
						"{{servicio_id_1}}",
						"viviendas",
						"{{vivienda_id_1}}"
					]
				}
			},
			"response": []
		},
		{
			"name": "Borrar una vivienda de un servicio que no existe",
			"event": [
				{
					"listen": "test",
					"script": {
						"exec": [
							"pm.test(\"Status code is 404\", function () {",
							"   pm.response.to.have.status(404);",
							"});",
							"",
							"pm.test(\"Get expected error message\", function () {",
							"   var data = pm.response.json();",
							"   pm.expect(data.apierror.message).to.eql(\"El servicio esta vacio.\");",
							"});",
							""
						],
						"type": "text/javascript",
						"packages": {}
					}
				}
			],
			"request": {
				"method": "DELETE",
				"header": [],
				"url": {
					"raw": "{{baseUrl}}/servicios/0/viviendas/{{vivienda_id_1}}",
					"host": [
						"{{baseUrl}}"
					],
					"path": [
						"servicios",
						"0",
						"viviendas",
						"{{vivienda_id_1}}"
					]
				}
			},
			"response": []
		}
	]
}